omdenalore/__init__.py
omdenalore/logger.py
omdenalore/computer_vision/__init__.py
omdenalore/computer_vision/activation_functions.py
omdenalore/computer_vision/augmentations.py
omdenalore/computer_vision/benchmark.py
omdenalore/computer_vision/green_pixel_detection.py
omdenalore/computer_vision/image_features.py
omdenalore/computer_vision/loss_functions_semantic.py
omdenalore/computer_vision/losses.py
omdenalore/computer_vision/metrics.py
omdenalore/computer_vision/object_detection.py
omdenalore/computer_vision/semantic_segmentation.py
omdenalore/computer_vision/utils.py
omdenalore/computer_vision/visualisations.py
omdenalore/datasets/__init__.py
omdenalore/datasets/download_datasets.py
omdenalore/natural_language_processing/__init__.py
omdenalore/natural_language_processing/ner.py
omdenalore/natural_language_processing/postprocess_text.py
omdenalore/natural_language_processing/preprocess_text.py
omdenalore/natural_language_processing/topic_modelling.py
omdenalore/natural_language_processing/twitter.py
omdenalore/natural_language_processing/utils.py
omdenalore/satellite_imagery/__init__.py
omdenalore/satellite_imagery/extract_gee.py
omdenalore/satellite_imagery/find_resolution.py
omdenalore/satellite_imagery/geom_to_json.py
omdenalore/satellite_imagery/preprocess_tiff.py
omdenalore/satellite_imagery/raster_summary.py
omdenalore/satellite_imagery/reprojecct_crs.py
omdenalore/satellite_imagery/utils.py
omdenalore-0.2.10.dist-info/LICENCE.txt
omdenalore-0.2.10.dist-info/METADATA
omdenalore-0.2.10.dist-info/WHEEL
omdenalore-0.2.10.dist-info/top_level.txt
omdenalore-0.2.10.dist-info/RECORD
